[
  {
    "question": "איפה חלם יעקב את חלום הסולם?",
    "options": [
      "חברון",
      "בית אל",
      "שכם",
      "באר שבע"
    ],
    "correct": 0
  },
  {
    "question": "איפה גבר שמשון על האריה?",
    "options": [
      "תמנה",
      "עקרון",
      "גת",
      "בית שמש"
    ],
    "correct": 0
  },
  {
    "question": "איפה הוכה גוליית?",
    "options": [
      "עמק האלה",
      "הר הגלבוע",
      "בית שמש",
      "ירושלים"
    ],
    "correct": 0
  },
  {
    "question": "איפה הייתה מלחמת ישראל עם עמלק בעת יציאת מצרים?",
    "options": [
      "מדבר פארן",
      "מדבר סין",
      "רפידים",
      "קדש"
    ],
    "correct": 0
  },
  {
    "question": "איפה נלקח חנניה, מישאל ועזריה לכבשן האש?",
    "options": [
      "שושן",
      "ירושלים",
      "בבל",
      "אשדוד"
    ],
    "correct": 0
  },
  {
    "question": "איפה בנה נח את התיבה?",
    "options": [
      "ארם",
      "הר אררט",
      "ארץ שנער",
      "לא נזכר"
    ],
    "correct": 0
  },
  {
    "question": "איפה הוכה עוזה כשנגע בארון?",
    "options": [
      "נביאים בגבעון",
      "פרץ עוזה",
      "ירושלים",
      "בית שמש"
    ],
    "correct": 0
  },
  {
    "question": "איפה הייתה ההתגלות הראשונה של ה' לשמואל?",
    "options": [
      "שילה",
      "גבעה",
      "נוב",
      "ירושלים"
    ],
    "correct": 0
  },
  {
    "question": "איפה התחבא שאול ביום המלכתו?",
    "options": [
      "מאחורי ההיכל",
      "בתוך הבית",
      "בין הכלים",
      "על הגג"
    ],
    "correct": 0
  },
  {
    "question": "איפה נכשל שאול באי השמדת עמלק?",
    "options": [
      "הר הכרמל",
      "עמק האלה",
      "עמק יזרעאל",
      "גבעת שאול"
    ],
    "correct": 0
  },
  {
    "question": "איפה נפגשו יעקב ועשיו לאחר שנים?",
    "options": [
      "שכם",
      "הר שעיר",
      "פְּנִיאֵל",
      "שדה אדום"
    ],
    "correct": 0
  },
  {
    "question": "איפה אליהו עלה בסערה השמיימה?",
    "options": [
      "הר חורב",
      "בית אל",
      "יריחו",
      "עבר הירדן"
    ],
    "correct": 0
  },
  {
    "question": "איפה חנה התפללה לה'?",
    "options": [
      "משכן שילה",
      "בית אל",
      "הר אפרים",
      "בית לחם"
    ],
    "correct": 0
  },
  {
    "question": "איפה הכה יואב את אבנר בן נר?",
    "options": [
      "גבעון",
      "חברון",
      "ירושלים",
      "שילה"
    ],
    "correct": 0
  },
  {
    "question": "איפה בנה נמרוד את בבל?",
    "options": [
      "ארץ כנען",
      "שנער",
      "אשור",
      "אררט"
    ],
    "correct": 0
  },
  {
    "question": "איפה בנה יעקב מזבח לאחר המאבק עם המלאך?",
    "options": [
      "פדנה ארם",
      "שכם",
      "בית אל",
      "פנואל"
    ],
    "correct": 0
  },
  {
    "question": "איפה אכלו בני ישראל את המן לראשונה?",
    "options": [
      "מדבר סין",
      "מדבר פארן",
      "רפידים",
      "הר סיני"
    ],
    "correct": 0
  },
  {
    "question": "איפה עמדו הר גריזים והר עיבל?",
    "options": [
      "ערבות מואב",
      "סמוך לשכם",
      "במדבר סיני",
      "בגלבוע"
    ],
    "correct": 0
  },
  {
    "question": "איפה נאמרה קללת ישעיהו על נבוכדנצר?",
    "options": [
      "שושן",
      "ירושלים",
      "בבל",
      "גוזן"
    ],
    "correct": 0
  },
  {
    "question": "איפה נגף ה' את עוזא על שליחת ידו לארון?",
    "options": [
      "גבעון",
      "נבו",
      "נחשון",
      "גורן נכון"
    ],
    "correct": 0
  },
  {
    "question": "איפה ברחו ישראל מהעמלקים והכנענים אחרי חטא המרגלים?",
    "options": [
      "חרמה",
      "קדש",
      "ערד",
      "עין גדי"
    ],
    "correct": 0
  },
  {
    "question": "איפה הוכה נבוכדנצר על ידי ה'?",
    "options": [
      "ארמונו בבבל",
      "עמק יהושפט",
      "שושן",
      "בתוך שדה קוצים"
    ],
    "correct": 0
  },
  {
    "question": "איפה ברח אליהו מפני איזבל?",
    "options": [
      "מדבר סיני",
      "באר שבע",
      "נחל קישון",
      "גלעד"
    ],
    "correct": 0
  },
  {
    "question": "איפה עלה שאול אל הכשפנית (אוב)?",
    "options": [
      "עין דור",
      "עין גדי",
      "נוב",
      "גבעון"
    ],
    "correct": 0
  },
  {
    "question": "איפה נשרפו הזהב והבגדים של עכן?",
    "options": [
      "גבעון",
      "גיא עכור",
      "עין גדי",
      "הרי עיבל"
    ],
    "correct": 0
  },
  {
    "question": "איפה קילל שמעי בן גרא את דוד בדברים קשים?",
    "options": [
      "ירושלים",
      "יריחו",
      "בצאתו מירושלים",
      "בחצור"
    ],
    "correct": 0
  },
  {
    "question": "איפה חפרו ליצחק עבדיו באר ושם לא רבו עליה?",
    "options": [
      "רחובות",
      "שובה",
      "באר שבע",
      "גרר"
    ],
    "correct": 0
  },
  {
    "question": "איפה נפגשו יעקב ועשיו אחרי שוב יעקב מחרן?",
    "options": [
      "פדן ארם",
      "סוכות",
      "הר שעיר",
      "מעבר יבוק"
    ],
    "correct": 0
  },
  {
    "question": "איפה הכו בני ישראל את סיחון מלך האמורי?",
    "options": [
      "עשתרות קרנים",
      "חשבון",
      "ערנון",
      "גלעד"
    ],
    "correct": 0
  },
  {
    "question": "איפה ביקש בלעם לקלל את ישראל?",
    "options": [
      "הר גריזים",
      "הר נבו",
      "במות בעל",
      "שדה מואב"
    ],
    "correct": 0
  },
  {
    "question": "איפה נפטר יוסף?",
    "options": [
      "מצרים",
      "שכם",
      "מדבר",
      "פדן ארם"
    ],
    "correct": 0
  },
  {
    "question": "איפה אמר יפתח הגלעדי את נדרו?",
    "options": [
      "מצפה",
      "גלעד",
      "שילה",
      "אפרים"
    ],
    "correct": 0
  },
  {
    "question": "איפה נאסרו חנניה מישאל ועזריה?",
    "options": [
      "שושן",
      "ארם",
      "בבל",
      "ירושלים"
    ],
    "correct": 0
  },
  {
    "question": "איפה קרא יהושע את התורה אחרי הכניסה לארץ?",
    "options": [
      "בין הר גריזים להר עיבל",
      "בשילה",
      "ביריחו",
      "בגלגל"
    ],
    "correct": 0
  },
  {
    "question": "איפה אמר ה' למשה: \"שַׁל נַעַלֶיךָ מֵעַל רַגְלֶיךָ\"?",
    "options": [
      "הר חורב",
      "סנה",
      "הר סיני",
      "הר נבו"
    ],
    "correct": 0
  },
  {
    "question": "איפה קיבלו בני ישראל את המן לראשונה?",
    "options": [
      "סיני",
      "מדבר שור",
      "מדבר סין",
      "מרה"
    ],
    "correct": 0
  },
  {
    "question": "איפה נמשח יהוא למלך?",
    "options": [
      "שומרון",
      "ירושלים",
      "רמות גלעד",
      "בית אל"
    ],
    "correct": 0
  },
  {
    "question": "איפה התפלל חזקיהו על חייו?",
    "options": [
      "בית המלך",
      "חצר הבית",
      "בית ה'",
      "על מיטתו"
    ],
    "correct": 0
  },
  {
    "question": "איפה נפל זמרי באש?",
    "options": [
      "תירצה",
      "שומרון",
      "גבעון",
      "ירושלים"
    ],
    "correct": 0
  },
  {
    "question": "איפה הכה דוד את גוליית?",
    "options": [
      "עמק האלה",
      "שילה",
      "גת",
      "בית לחם"
    ],
    "correct": 0
  },
  {
    "question": "איפה נחה תיבת נח לאחר המבול?",
    "options": [
      "הרי מואב",
      "הר סיני",
      "הרי אררט",
      "הר חרמון"
    ],
    "correct": 0
  },
  {
    "question": "איפה ראה יעקב את אלוהים פנים אל פנים?",
    "options": [
      "בית אל",
      "פנואל",
      "הר המוריה",
      "מצפה גלעד"
    ],
    "correct": 0
  },
  {
    "question": "איפה פגש יוסף את אחיו ששלח אביו לחפש?",
    "options": [
      "שכם",
      "חברון",
      "דתן",
      "גת"
    ],
    "correct": 0
  },
  {
    "question": "איפה התגלה ה' אל שלמה בפעם הראשונה?",
    "options": [
      "ירושלים",
      "גבעון",
      "שילה",
      "מצפה"
    ],
    "correct": 0
  },
  {
    "question": "איפה התגלה ה' אל שלמה בפעם השנייה?",
    "options": [
      "גבעון",
      "שילה",
      "ירושלים",
      "חברון"
    ],
    "correct": 0
  },
  {
    "question": "איפה בנה ירבעם את בית הבמות הראשון?",
    "options": [
      "דן",
      "שומרון",
      "בית אל",
      "תל רמות"
    ],
    "correct": 0
  },
  {
    "question": "איפה רץ אחימעץ להביא את הבשורה לדוד?",
    "options": [
      "מדבר יהודה",
      "מעלה בית חורון",
      "דרך הככר",
      "דרך הר אפרים"
    ],
    "correct": 0
  },
  {
    "question": "איפה התחפש אחאב כדי שלא יכירוהו במלחמה?",
    "options": [
      "שומרון",
      "רמות גלעד",
      "בית אל",
      "גבעון"
    ],
    "correct": 0
  },
  {
    "question": "איפה נמצא שלמה את הנשים המריבות על הילד?",
    "options": [
      "גבעון",
      "שילה",
      "בית המלך בירושלים",
      "באר שבע"
    ],
    "correct": 0
  },
  {
    "question": "איפה עלה אליהו השמימה?",
    "options": [
      "יריחו",
      "ירדן",
      "גלעד",
      "הר הכרמל"
    ],
    "correct": 0
  },
  {
    "question": "איפה נפל שאול על חרבו?",
    "options": [
      "הר תבור",
      "הר גלבוע",
      "עמק יזרעאל",
      "הר אפרים"
    ],
    "correct": 0
  },
  {
    "question": "איפה קרא דוד: \"אבשלום בני, בני!\"?",
    "options": [
      "שדה הקרב",
      "שער העיר",
      "במדבר",
      "גת"
    ],
    "correct": 0
  },
  {
    "question": "איפה פשטו הפלשתים את מחנה ישראל במלחמת הגלבוע?",
    "options": [
      "בית שאן",
      "גת",
      "שילה",
      "הר תבור"
    ],
    "correct": 0
  },
  {
    "question": "איפה נלחם שמשון באלף פלשתים עם לחי חמור?",
    "options": [
      "תמנתה",
      "לחי",
      "עין גדי",
      "צרעה"
    ],
    "correct": 0
  },
  {
    "question": "איפה ביקשו הפלשתים שדוד לא יילחם איתם נגד שאול?",
    "options": [
      "אפק",
      "גת",
      "שכם",
      "עקרון"
    ],
    "correct": 0
  },
  {
    "question": "איפה התגלה המלאך אל גדעון?",
    "options": [
      "בבית אל",
      "בעפרה",
      "בגבעון",
      "בגת"
    ],
    "correct": 0
  },
  {
    "question": "איפה נרצח איש בושת בן שאול?",
    "options": [
      "גבעון",
      "מחניים",
      "בית אל",
      "רמות"
    ],
    "correct": 0
  },
  {
    "question": "איפה התחבאו מרגלי יהושע?",
    "options": [
      "יריחו",
      "בית רחב",
      "שילה",
      "גת"
    ],
    "correct": 0
  },
  {
    "question": "איפה אמרה מרים הנביאה שירה?",
    "options": [
      "על הים",
      "במדבר שור",
      "ליד הר סיני",
      "ברפידים"
    ],
    "correct": 0
  },
  {
    "question": "איפה התחבא דוד כשהיה נרדף על ידי שאול?",
    "options": [
      "מצפה",
      "עין גדי",
      "גת",
      "גבעון"
    ],
    "correct": 0
  },
  {
    "question": "איפה נבנה המשכן אחרי חציית הירדן?",
    "options": [
      "שילה",
      "גלגל",
      "גבעון",
      "ירושלים"
    ],
    "correct": 0
  },
  {
    "question": "איפה קברו את יהושע בן נון?",
    "options": [
      "חברון",
      "תמנת סרח",
      "בית אל",
      "גבעת פנחס"
    ],
    "correct": 0
  },
  {
    "question": "איפה נשלח אליעזר למצוא אישה ליצחק?",
    "options": [
      "ארם נהריים",
      "אור כשדים",
      "מצרים",
      "גלעד"
    ],
    "correct": 0
  },
  {
    "question": "איפה הציע לוט את בנותיו במקום האורחים?",
    "options": [
      "צוער",
      "סדום",
      "עמורה",
      "הרים"
    ],
    "correct": 0
  },
  {
    "question": "איפה נגלה ה' אל שמואל לראשונה?",
    "options": [
      "שילה",
      "בית לחם",
      "גבעון",
      "נוב"
    ],
    "correct": 0
  },
  {
    "question": "איפה נאמר \"מה נורא המקום הזה\"?",
    "options": [
      "שכם",
      "הר סיני",
      "בית אל",
      "ירושלים"
    ],
    "correct": 0
  },
  {
    "question": "איפה פגש משה את בנות יתרו?",
    "options": [
      "מדבר סין",
      "מדבר מדין",
      "עין גדי",
      "רפידים"
    ],
    "correct": 0
  },
  {
    "question": "איפה קרא ה' אל משה מתוך הסנה?",
    "options": [
      "חורב",
      "סיני",
      "מדין",
      "רעמסס"
    ],
    "correct": 0
  },
  {
    "question": "איפה ראה בלעם את המלאך עומד עם חרב שלופה?",
    "options": [
      "שדה מואב",
      "בין הכרמים",
      "הר העברים",
      "במדבר צין"
    ],
    "correct": 0
  },
  {
    "question": "איפה הרגו פנחס ואנשי ישראל את זמרי וכזבי?",
    "options": [
      "ערבות מואב",
      "קדש",
      "בית פעור",
      "הר נבו"
    ],
    "correct": 0
  },
  {
    "question": "איפה סופר ספר התורה ע\"י עזרא הסופר לציבור?",
    "options": [
      "שילה",
      "ירושלים",
      "הר גריזים",
      "בית אל"
    ],
    "correct": 0
  },
  {
    "question": "איפה התקבץ כל העם אחרי מות יהושע?",
    "options": [
      "שילה",
      "מצפה",
      "גלגל",
      "שכם"
    ],
    "correct": 0
  },
  {
    "question": "איפה שלח יעקב את יוסף לראות את אחיו?",
    "options": [
      "גת",
      "שכם",
      "חברון",
      "רעמסס"
    ],
    "correct": 0
  },
  {
    "question": "איפה נגף ה' את מחנה סנחריב?",
    "options": [
      "שומרון",
      "ירושלים",
      "לכיש",
      "נוב"
    ],
    "correct": 0
  },
  {
    "question": "איפה נאמר \"ויחר אף ה' במשה\"?",
    "options": [
      "בהר סיני",
      "במדבר מדין",
      "ליד הסנה",
      "על שפת ים סוף"
    ],
    "correct": 0
  },
  {
    "question": "איפה ראה משה את הארץ ולא נכנס?",
    "options": [
      "הר העברים",
      "הר נבו",
      "הר הכרמל",
      "פסגת פיסגה"
    ],
    "correct": 0
  },
  {
    "question": "איפה הוקע יהושע את מלך עי?",
    "options": [
      "על שער העיר",
      "על עץ",
      "בבור",
      "על אבן"
    ],
    "correct": 0
  },
  {
    "question": "איפה נאמר \"ויקח משה את עצמות יוסף עמו\"?",
    "options": [
      "רעמסס",
      "סוכות",
      "ים סוף",
      "אלים"
    ],
    "correct": 0
  },
  {
    "question": "איפה נשבע ה' שלא יכניס דור המדבר לארץ?",
    "options": [
      "מדבר שור",
      "מדבר פארן",
      "קדש",
      "במדבר צין"
    ],
    "correct": 0
  },
  {
    "question": "איפה קברו את שרה?",
    "options": [
      "בית לחם",
      "שכם",
      "מערת המכפלה",
      "הר נבו"
    ],
    "correct": 0
  },
  {
    "question": "איפה נקבר שמואל?",
    "options": [
      "שילה",
      "רמה",
      "גבעון",
      "ירושלים"
    ],
    "correct": 0
  },
  {
    "question": "איפה הביאו ישראל אבנים להקים מזבח אחרי חציית הירדן?",
    "options": [
      "בית אל",
      "גלגל",
      "יריחו",
      "גבעון"
    ],
    "correct": 0
  },
  {
    "question": "איפה הסתירו המרגלים את עצמם כאשר חיפשו אותם אנשי יריחו?",
    "options": [
      "בעליית הגג",
      "בחומת העיר",
      "בבור מים",
      "מאחורי דלת"
    ],
    "correct": 0
  },
  {
    "question": "איפה נבקע הירדן לראשונה בידי ישראל?",
    "options": [
      "מול יריחו",
      "מול שילה",
      "בגלגל",
      "מול בית אל"
    ],
    "correct": 0
  },
  {
    "question": "איפה התקבצו השבטים נגד פילגש בגבעה?",
    "options": [
      "שילה",
      "מצפה",
      "בית אל",
      "גבעון"
    ],
    "correct": 0
  },
  {
    "question": "איפה התחבאו שלושת ימי המרגלים ששלח יהושע?",
    "options": [
      "בגלגל",
      "בהר",
      "במדבר",
      "בעין"
    ],
    "correct": 0
  },
  {
    "question": "איפה נשלח ירמיהו לקנות חגורת פשתן?",
    "options": [
      "לבבל",
      "לפרת",
      "לבית לחם",
      "לגת"
    ],
    "correct": 0
  },
  {
    "question": "איפה נרצח הבל ע\"י קין?",
    "options": [
      "שדה",
      "עיר נוד",
      "הר הגלעד",
      "לא נכתב במפורש"
    ],
    "correct": 0
  },
  {
    "question": "איפה נרצח זכריה בן יהוידע?",
    "options": [
      "בחצר בית ה'",
      "בהר הבית",
      "בעיר דוד",
      "בשער העליון"
    ],
    "correct": 0
  },
  {
    "question": "איפה נרצח גדליה בן אחיקם?",
    "options": [
      "מצפה",
      "שכם",
      "רמה",
      "יריחו"
    ],
    "correct": 0
  },
  {
    "question": "איפה נרצח אבנר בן נר?",
    "options": [
      "בחברון",
      "בגבעון",
      "בירושלים",
      "במדבר"
    ],
    "correct": 0
  },
  {
    "question": "איפה נרצח עמשא בן יתר?",
    "options": [
      "בגבעון",
      "בחברון",
      "בשער העיר",
      "במקרא גדרה"
    ],
    "correct": 0
  },
  {
    "question": "איפה נרצח איגל בן יוסף ע\"י שאול?",
    "options": [
      "לא נרצח",
      "בגלבוע",
      "בשדה",
      "לא היה מישהו כזה"
    ],
    "correct": 0
  },
  {
    "question": "איפה נרצח סיסרא?",
    "options": [
      "באוהל יעל",
      "ליד נחל קישון",
      "בהר תבור",
      "בגבעון"
    ],
    "correct": 0
  },
  {
    "question": "איפה נרצח אמנון בן דוד?",
    "options": [
      "בחצר בית אבשלום",
      "בביתו בירושלים",
      "בגזיזה של אבשלום",
      "בשדה"
    ],
    "correct": 0
  },
  {
    "question": "איפה נרצח נבות היזרעאלי?",
    "options": [
      "בשער העיר",
      "בכרמו",
      "בירושלים",
      "בהר הכרמל"
    ],
    "correct": 0
  },
  {
    "question": "איפה נרצח פכחיה בן מנחם?",
    "options": [
      "בשומרון",
      "בירושלים",
      "בשילה",
      "בגת"
    ],
    "correct": 0
  },
  {
    "question": "איפה נרצח שלום בן יבש?",
    "options": [
      "לא נמסר מקום",
      "בירושלים",
      "בשומרון",
      "בהר אפרים"
    ],
    "correct": 0
  },
  {
    "question": "איפה נרצח צדקיהו (אחרון מלכי יהודה)?",
    "options": [
      "לא נרצח – הוגלה",
      "בבית ה'",
      "ליד יריחו",
      "בשבי בבבל"
    ],
    "correct": 0
  },
  {
    "question": "איפה נרצח שאול המלך?",
    "options": [
      "בהר הגלבוע",
      "בגבעת שאול",
      "בשערי יריחו",
      "בשומרון"
    ],
    "correct": 0
  },
  {
    "question": "איפה נרצח אחאב מלך ישראל?",
    "options": [
      "ברמות גלעד",
      "בשומרון",
      "בהר הכרמל",
      "בירושלים"
    ],
    "correct": 0
  },
  {
    "question": "איפה נרצח אוריה החתי לבקשת דוד?",
    "options": [
      "בחזית הקרב",
      "ליד ירושלים",
      "בהר אפרים",
      "ליד חברון"
    ],
    "correct": 0
  },
  {
    "question": "איפה נרצח זמרי לאחר ששרף את הארמון?",
    "options": [
      "תירצה",
      "שומרון",
      "גבעון",
      "לא נרצח אלא התאבד"
    ],
    "correct": 0
  }
]